tabular_entropy-0.1.1.dist-info/METADATA
tabular_entropy-0.1.1.dist-info/WHEEL
tabular_entropy/__init__.py
tabular_entropy/tabular_entropy.cpython-39-x86_64-linux-gnu.so
tabular_entropy-0.1.1.dist-info/RECORD
